webbrowserdownloader/__init__.py
webbrowserdownloader/browser.py
webbrowserdownloader-0.1.dist-info/LICENSE
webbrowserdownloader-0.1.dist-info/METADATA
webbrowserdownloader-0.1.dist-info/WHEEL
webbrowserdownloader-0.1.dist-info/top_level.txt
webbrowserdownloader-0.1.dist-info/RECORD
